latexrestricted/__init__.py
latexrestricted/_anypath.py
latexrestricted/_latex_config.py
latexrestricted/_restricted_pathlib.py
latexrestricted/_restricted_subprocess.py
latexrestricted/err.py
latexrestricted/fmtversion.py
latexrestricted/version.py
latexrestricted-0.6.2.dist-info/CHANGELOG.md
latexrestricted-0.6.2.dist-info/LICENSE.txt
latexrestricted-0.6.2.dist-info/METADATA
latexrestricted-0.6.2.dist-info/WHEEL
latexrestricted-0.6.2.dist-info/top_level.txt
latexrestricted-0.6.2.dist-info/RECORD
