Metadata-Version: 2.1
Name: latexrestricted
Version: 0.6.2
Summary: Library for creating Python executables compatible with LaTeX restricted shell escape
Author-email: "Geoffrey M. Poore" <gpoore@gmail.com>
License: latexrestricted Python package
Project-URL: homepage, https://github.com/gpoore/latexrestricted
Project-URL: repository, https://github.com/gpoore/latexrestricted
Project-URL: changelog, https://github.com/gpoore/latexrestricted/blob/main/CHANGELOG.md
Keywords: LaTeX,security,restricted shell escape
Classifier: Development Status :: 4 - Beta
Classifier: Programming Language :: Python
Classifier: Environment :: Console
Classifier: Intended Audience :: Developers
Classifier: License :: OSI Approved
Classifier: Operating System :: OS Independent
Classifier: Topic :: Text Processing :: Markup :: LaTeX
Requires-Python: >=3.8
License-File: LICENSE.txt
License-File: CHANGELOG.md
